odoo/addons/pos_require_product_quantity/README.rst
odoo/addons/pos_require_product_quantity/__init__.py
odoo/addons/pos_require_product_quantity/__manifest__.py
odoo/addons/pos_require_product_quantity/i18n/es.po
odoo/addons/pos_require_product_quantity/i18n/pos_require_product_quantity.pot
odoo/addons/pos_require_product_quantity/models/__init__.py
odoo/addons/pos_require_product_quantity/models/pos_config.py
odoo/addons/pos_require_product_quantity/readme/CONTRIBUTORS.rst
odoo/addons/pos_require_product_quantity/readme/DESCRIPTION.rst
odoo/addons/pos_require_product_quantity/static/description/icon.png
odoo/addons/pos_require_product_quantity/static/description/index.html
odoo/addons/pos_require_product_quantity/static/src/js/screens.js
odoo/addons/pos_require_product_quantity/views/assets.xml
odoo/addons/pos_require_product_quantity/views/pos_config.xml
odoo12_addon_pos_require_product_quantity-12.0.0.2.1.dist-info/METADATA
odoo12_addon_pos_require_product_quantity-12.0.0.2.1.dist-info/WHEEL
odoo12_addon_pos_require_product_quantity-12.0.0.2.1.dist-info/top_level.txt
odoo12_addon_pos_require_product_quantity-12.0.0.2.1.dist-info/RECORD
