Metadata-Version: 2.1
Name: odoo12-addon-pos-require-product-quantity
Version: 12.0.0.2.1
Summary: A popup is shown if product quantity is set to 0 for one or more order lines when clicking on "Payment" button.
Home-page: https://github.com/OCA/pos
Author: Coop IT Easy SCRLfs, Odoo Community Association (OCA)
Author-email: support@odoo-community.org
License: AGPL-3
Platform: UNKNOWN
Classifier: Programming Language :: Python
Classifier: Framework :: Odoo
Classifier: Framework :: Odoo :: 12.0
Classifier: License :: OSI Approved :: GNU Affero General Public License v3
Requires-Python: >=3.5
Requires-Dist: odoo (<12.1dev,>=12.0a)
